tap/__init__.py
tap/api/__init__.py
tap/api/client.py
tap/api/discovery.py
tap/api/schema.py
tap/api/stream.py
tap/api/sync.py
tap/api/test.py
tap/api/transform.py
tap_core-0.0.3.dist-info/LICENSE
tap_core-0.0.3.dist-info/METADATA
tap_core-0.0.3.dist-info/WHEEL
tap_core-0.0.3.dist-info/entry_points.txt
tap_core-0.0.3.dist-info/top_level.txt
tap_core-0.0.3.dist-info/RECORD
