Metadata-Version: 2.1
Name: tap-core
Version: 0.0.3
Summary: Singer.io Tap Core features
Home-page: https://gitlab.com/singer-core/tap-core
Author: Eddy ∆
Author-email: edrdelta@gmail.com
License: Apache License 2.0
Project-URL: Documentation, https://singer-core.gitlab.io/tap-core
Project-URL: Releases, https://gitlab.com/singer-core/tap-core/-/releases
Project-URL: Changelog, https://gitlab.com/singer-core/tap-core/blob/main/CHANGELOG.rst
Project-URL: Issue Tracker, https://gitlab.com/singer-core/tap-core/issues
Project-URL: Bug Tracker, https://gitlab.com/singer-core/target-core/issues/service_desk
Keywords: singer,tap,tap-core,target,target-core,target-s3-jsonl,target-s3-json,etl
Classifier: Development Status :: 1 - Planning
Classifier: Operating System :: OS Independent
Classifier: License :: OSI Approved :: Apache Software License
Classifier: Programming Language :: Python :: 3 :: Only
Classifier: Programming Language :: Python :: 3.9
Requires-Python: >=3.9
License-File: LICENSE
Requires-Dist: singer-python (~=5.0)
Requires-Dist: aiohttp (~=3.0)
Provides-Extra: deploy
Requires-Dist: twine ; extra == 'deploy'
Provides-Extra: dist
Requires-Dist: build ; extra == 'dist'
Provides-Extra: docs
Requires-Dist: sphinx ; extra == 'docs'
Requires-Dist: sphinx-rtd-theme ; extra == 'docs'
Requires-Dist: sphinx-automodapi ; extra == 'docs'
Requires-Dist: numpydoc ; extra == 'docs'
Provides-Extra: lint
Requires-Dist: flake8 ; extra == 'lint'
Provides-Extra: static
Requires-Dist: mypy ; extra == 'static'
Provides-Extra: test
Requires-Dist: pytest-asyncio ; extra == 'test'
Requires-Dist: pytest-cov ; extra == 'test'
